Flask_No_Cache/__init__.py
Flask_No_Cache/utils.py
Flask_No_Cache-1.0.dist-info/LICENSE
Flask_No_Cache-1.0.dist-info/METADATA
Flask_No_Cache-1.0.dist-info/WHEEL
Flask_No_Cache-1.0.dist-info/top_level.txt
Flask_No_Cache-1.0.dist-info/RECORD
