Metadata-Version: 2.1
Name: Flask-No-Cache
Version: 1.0
Summary: Cache control for Flask
Home-page: https://github.com/vwt-digital/flask-no-cache
Author: VolkerWessels Telecom
Author-email: opensource@vwt.digital
License: UNKNOWN
Platform: UNKNOWN
Classifier: Programming Language :: Python :: 3
Classifier: License :: OSI Approved :: GNU General Public License v3 (GPLv3)
Classifier: Operating System :: OS Independent
Requires-Python: >=3.6
